README.md
lifetimes/__init__.py
lifetimes/generate_data.py
lifetimes/plotting.py
lifetimes/utils.py
lifetimes/version.py
lifetimes/datasets/CDNOW_master.txt
lifetimes/datasets/CDNOW_sample.txt
lifetimes/datasets/__init__.py
lifetimes/datasets/cdnow_customers_summary.csv
lifetimes/datasets/cdnow_customers_summary_with_transactions.csv
lifetimes/datasets/donations.csv
lifetimes/datasets/example_transactions.csv
lifetimes/fitters/__init__.py
lifetimes/fitters/beta_geo_beta_binom_fitter.py
lifetimes/fitters/beta_geo_fitter.py
lifetimes/fitters/gamma_gamma_fitter.py
lifetimes/fitters/modified_beta_geo_fitter.py
lifetimes/fitters/pareto_nbd_fitter.py
Lifetimes-0.11.2.dist-info/LICENSE.txt
Lifetimes-0.11.2.dist-info/METADATA
Lifetimes-0.11.2.dist-info/WHEEL
Lifetimes-0.11.2.dist-info/top_level.txt
Lifetimes-0.11.2.dist-info/RECORD
