Metadata-Version: 2.1
Name: Lifetimes
Version: 0.11.2
Summary: Measure customer lifetime value in Python
Home-page: https://github.com/CamDavidsonPilon/lifetimes
Author: Cam Davidson-Pilon
Author-email: cam.davidson.pilon@gmail.com
License: MIT
Keywords: customer lifetime value,clv,ltv,BG/NBD,pareto/NBD,frequency,recency
Platform: UNKNOWN
Classifier: Development Status :: 4 - Beta
Classifier: License :: OSI Approved :: MIT License
Classifier: Programming Language :: Python
Classifier: Programming Language :: Python :: 2.7
Classifier: Programming Language :: Python :: 3.5
Classifier: Topic :: Scientific/Engineering
Requires-Dist: numpy (>=1.10.0)
Requires-Dist: scipy (>=1.0.0)
Requires-Dist: pandas (>=0.24.0)
Requires-Dist: autograd (>=1.2.0)
Requires-Dist: dill (>=0.2.6)
